anonfiles_directlink/__init__.py
anonfiles_directlink/direct_link.py
anonfiles_directlink/example.py
anonfiles_directlink-1.2.dist-info/METADATA
anonfiles_directlink-1.2.dist-info/WHEEL
anonfiles_directlink-1.2.dist-info/licenses/LICENSE
anonfiles_directlink-1.2.dist-info/RECORD
