Metadata-Version: 2.1
Name: anonfiles-directlink
Version: 1.2
Summary: Generate anonfiles direct link
Project-URL: Homepage, https://github.com/player2I0/anonfiles-directlink
Project-URL: Bug Tracker, https://github.com/player2I0/anonfiles-directlink/issues
Author-email: player210 <egorbubenov228@gmail.com>
License-File: LICENSE
Classifier: License :: OSI Approved :: MIT License
Classifier: Operating System :: OS Independent
Classifier: Programming Language :: Python :: 3
Requires-Python: >=3
